even_parity_generetor/main.v
module evenparity(in,p);
input [3:0] in;
output p;
assign p= in[3]^in[2]^in[1]^in[0];
endmodule

// even parity checked by this , if there if even number of i's in given data so 
// p = zero or wise it high 
// test bench in v 
module tb;
reg [3:0] in;
wire p;
evenparity dut(in,p);
initial begin
    $dumpvars(0,tb);
    $dumpfile("tets.vcd");
    repeat(10) begin
        in= $random % 4'b1111; #10
        $monitor("time :  %d in =%b parity %b",$time,in,p);
        
    end
    #10 $finish;
end

endmodule

even_parity_generetor/dump.vcd
$date
	Tue Jul 22 15:37:43 2025
$end
$version
	Icarus Verilog
$end
$timescale
	1s
$end
$scope module tb $end
$var wire 1 ! p $end
$var reg 4 " in [3:0] $end
$scope module dut $end
$var wire 4 # in [3:0] $end
$var wire 1 ! p $end
$upscope $end
$upscope $end
$enddefinitions $end
$comment Show the parameter values. $end
$dumpall
$end
#0
$dumpvars
b1000 #
b1000 "
1!
$end
#10
0!
b1100 "
b1100 #
#20
1!
b111 "
b111 #
#30
1!
b10 "
b10 #
#40
0!
b1100 "
b1100 #
#50
1!
b10 "
b10 #
#60
0!
b101 "
b101 #
#70
1!
b111 "
b111 #
#80
0!
b110 "
b110 #
#90
1!
b100 "
b100 #
