fifo/synchronous_fifo/fifo.v
module fifo1 #(parameter fifo_depth=8,
                parameter data_width=32) (
                    input clk,
                    input rst_n,
                    input cs,
                    input wr_en,
                    input rd_en,
                    input [data_width-1:0] data_in,
                    output reg [data_width-1:0] data_out,
                    output empty,
                    output full
                );
// find the counter bit according to depth of fifo 
localparam  fifo_depth_log = $clog2(fifo_depth) ;
// define the dimension of aaray to store the data
reg [data_width-1:0]fifo [0:fifo_depth-1];
// poniter decalartion 
reg [fifo_depth_log:0] write_ptr;  // here we take 1 extra bit in counter for calculation of full and empty 
reg [fifo_depth_log:0] read_ptr; // condition 

// write operation 
always @(posedge clk or negedge rst_n)
  begin
    if (!rst_n)
      begin
        write_ptr <= 0;
      end
      else if (cs && wr_en && !full) begin
   // thid condition for the data in fifo data <= data_in 
           fifo [write_ptr[fifo_depth_log-1:0]] <=   data_in;
           write_ptr <= write_ptr + 1'b1;        
      end
  end
  // read operation

always @(posedge clk or negedge rst_n)
  begin
    if (!rst_n)
     begin
        read_ptr <= 0;
        data_out <= 0;
    
     end
     else if (cs && rd_en && !empty) begin
        data_out <= fifo[read_ptr[fifo_depth_log-1:0]];
        read_ptr <= read_ptr + 1'b1;
     end
  end

  // flag signala and control logic 
  assign  empty = (read_ptr == write_ptr);
  assign full = (read_ptr == ({~write_ptr[fifo_depth_log],write_ptr[fifo_depth_log-1:0]}));


endmodule

// all module should declare in this way to make the file function well

fifo/synchronous_fifo/fifo_tb.v
`timescale 1ns/1ns
`include "fifo.v"
module tb();
parameter fifo_depth=8;
parameter data_width=32;
reg clk,rst_n,cs,wr_en,rd_en;
reg [data_width-1:0] data_in;
wire [data_width-1:0] data_out;
wire empty,full;
/*
fifo1 #(fifo_depth,
            data_width) dut (
                    clk,
                    rst_n,
                     cs,
                    wr_en,
                    rd_en,
                    data_in,
                    data_out,
                    empty,
                    full);*/
 


 fifo1 #(.fifo_depth(fifo_depth),
            .data_width(data_width)) dut (
                    .clk(clk),
                    .rst_n(rst_n),
                     .cs(cs),
                    .wr_en(wr_en),
                    .rd_en(rd_en),
                    .data_in(data_in),
                    .data_out(data_out),
                    .empty(empty),
                    .full(full)); 
  // signal stimulation 
initial begin
    clk=0;
end

      always begin #5 clk=~clk; end

   // clock generate for this simulation 
  // create task 
  task wrt_data(input [data_width-1:0] d_in);
    begin 
        @ (posedge clk)
        cs=1; wr_en =1;
        data_in = d_in;
        $display($time, " data_ enter %0d",data_in);
        @ (posedge clk)
        cs=1; wr_en =0;

    end
  endtask

  task rd_data ();
    begin
        @(posedge clk)
        cs=1; rd_en=1;
        //#1
        
        @(posedge clk)
        $display($time, " data_ read  %0d",data_out);
        cs =1; rd_en=0;
    end
  endtask
// create signals for test bench 
initial begin
    #1; 
    rst_n =0; rd_en =0; wr_en =0;
    @(posedge clk)
    rst_n =1;
    $display ($time, "\n scenario 1");
    wrt_data(1);
    wrt_data(20);
    wrt_data(120);
    rd_data();
    rd_data();
    rd_data();
    rd_data();
    // second test 
    $display($time,"\n second test");
    for(integer i=0;i<fifo_depth;i=1+i) begin
        wrt_data(2**i);
        rd_data();
    end
    $display($time,"\n second test");
    for(integer i=0;i<fifo_depth;i=1+i) begin
        wrt_data(2**i);
       // rd_data();
    end
    $display($time,"\n second test");
    for(integer i=0;i<fifo_depth;i=1+i) begin
       // wrt_data(2**i);
        rd_data();
    end   
  #50 $finish;

end

  initial begin
      $dumpfile("dump.vcd"); $dumpvars;
   end
endmodule

fifo/synchronous_fifo/dump.vcd
$date
	Wed Jul 30 09:31:21 2025
$end
$version
	Icarus Verilog
$end
$timescale
	1ns
$end
$scope module tb $end
$var wire 1 ! full $end
$var wire 1 " empty $end
$var wire 32 # data_out [31:0] $end
$var parameter 32 $ data_width $end
$var parameter 32 % fifo_depth $end
$var reg 1 & clk $end
$var reg 1 ' cs $end
$var reg 32 ( data_in [31:0] $end
$var reg 1 ) rd_en $end
$var reg 1 * rst_n $end
$var reg 1 + wr_en $end
$scope module dut $end
$var wire 1 & clk $end
$var wire 1 ' cs $end
$var wire 32 , data_in [31:0] $end
$var wire 1 ) rd_en $end
$var wire 1 * rst_n $end
$var wire 1 + wr_en $end
$var wire 1 ! full $end
$var wire 1 " empty $end
$var parameter 32 - data_width $end
$var parameter 32 . fifo_depth $end
$var parameter 32 / fifo_depth_log $end
$var reg 32 0 data_out [31:0] $end
$var reg 4 1 read_ptr [3:0] $end
$var reg 4 2 write_ptr [3:0] $end
$upscope $end
$scope begin $ivl_for_loop0 $end
$var integer 32 3 i [31:0] $end
$upscope $end
$scope begin $ivl_for_loop1 $end
$var integer 32 4 i [31:0] $end
$upscope $end
$scope begin $ivl_for_loop2 $end
$var integer 32 5 i [31:0] $end
$upscope $end
$scope task rd_data $end
$upscope $end
$scope task wrt_data $end
$var reg 32 6 d_in [31:0] $end
$upscope $end
$upscope $end
$enddefinitions $end
$comment Show the parameter values. $end
$dumpall
b11 /
b1000 .
b100000 -
b1000 %
b100000 $
$end
#0
$dumpvars
bx 6
bx 5
bx 4
bx 3
bx 2
bx 1
bx 0
bx ,
x+
x*
x)
bx (
x'
0&
bx #
x"
x!
$end
#1
0!
1"
b0 2
b0 #
b0 0
b0 1
0+
0)
0*
#5
b1 6
1*
1&
#10
0&
#15
0"
b1 2
b1 (
b1 ,
1+
1'
1&
#20
0&
#25
b10100 6
0+
1&
#30
0&
#35
b10 2
b10100 (
b10100 ,
1+
1&
#40
0&
#45
b1111000 6
0+
1&
#50
0&
#55
b11 2
b1111000 (
b1111000 ,
1+
1&
#60
0&
#65
0+
1&
#70
0&
#75
b1 1
b1 #
b1 0
1)
1&
#80
0&
#85
0)
1&
#90
0&
#95
b10 1
b10100 #
b10100 0
1)
1&
#100
0&
#105
0)
1&
#110
0&
#115
1"
b11 1
b1111000 #
b1111000 0
1)
1&
#120
0&
#125
0)
1&
#130
0&
#135
1)
1&
#140
0&
#145
b1 6
b0 3
0)
1&
#150
0&
#155
0"
b100 2
b1 (
b1 ,
1+
1&
#160
0&
#165
0+
1&
#170
0&
#175
1"
b100 1
b1 #
b1 0
1)
1&
#180
0&
#185
b10 6
b1 3
0)
1&
#190
0&
#195
0"
b101 2
b10 (
b10 ,
1+
1&
#200
0&
#205
0+
1&
#210
0&
#215
1"
b101 1
b10 #
b10 0
1)
1&
#220
0&
#225
b100 6
b10 3
0)
1&
#230
0&
#235
0"
b110 2
b100 (
b100 ,
1+
1&
#240
0&
#245
0+
1&
#250
0&
#255
1"
b110 1
b100 #
b100 0
1)
1&
#260
0&
#265
b1000 6
b11 3
0)
1&
#270
0&
#275
0"
b111 2
b1000 (
b1000 ,
1+
1&
#280
0&
#285
0+
1&
#290
0&
#295
1"
b111 1
b1000 #
b1000 0
1)
1&
#300
0&
#305
b10000 6
b100 3
0)
1&
#310
0&
#315
0"
b1000 2
b10000 (
b10000 ,
1+
1&
#320
0&
#325
0+
1&
#330
0&
#335
1"
b1000 1
b10000 #
b10000 0
1)
1&
#340
0&
#345
b100000 6
b101 3
0)
1&
#350
0&
#355
0"
b1001 2
b100000 (
b100000 ,
1+
1&
#360
0&
#365
0+
1&
#370
0&
#375
1"
b1001 1
b100000 #
b100000 0
1)
1&
#380
0&
#385
b1000000 6
b110 3
0)
1&
#390
0&
#395
0"
b1010 2
b1000000 (
b1000000 ,
1+
1&
#400
0&
#405
0+
1&
#410
0&
#415
1"
b1010 1
b1000000 #
b1000000 0
1)
1&
#420
0&
#425
b10000000 6
b111 3
0)
1&
#430
0&
#435
0"
b1011 2
b10000000 (
b10000000 ,
1+
1&
#440
0&
#445
0+
1&
#450
0&
#455
1"
b1011 1
b10000000 #
b10000000 0
1)
1&
#460
0&
#465
b1 6
b0 4
b1000 3
0)
1&
#470
0&
#475
0"
b1100 2
b1 (
b1 ,
1+
1&
#480
0&
#485
b10 6
b1 4
0+
1&
#490
0&
#495
b1101 2
b10 (
b10 ,
1+
1&
#500
0&
#505
b100 6
b10 4
0+
1&
#510
0&
#515
b1110 2
b100 (
b100 ,
1+
1&
#520
0&
#525
b1000 6
b11 4
0+
1&
#530
0&
#535
b1111 2
b1000 (
b1000 ,
1+
1&
#540
0&
#545
b10000 6
b100 4
0+
1&
#550
0&
#555
b0 2
b10000 (
b10000 ,
1+
1&
#560
0&
#565
b100000 6
b101 4
0+
1&
#570
0&
#575
b1 2
b100000 (
b100000 ,
1+
1&
#580
0&
#585
b1000000 6
b110 4
0+
1&
#590
0&
#595
b10 2
b1000000 (
b1000000 ,
1+
1&
#600
0&
#605
b10000000 6
b111 4
0+
1&
#610
0&
#615
1!
b11 2
b10000000 (
b10000000 ,
1+
1&
#620
0&
#625
b0 5
b1000 4
0+
1&
#630
0&
#635
0!
b1100 1
b1 #
b1 0
1)
1&
#640
0&
#645
b1 5
0)
1&
#650
0&
#655
b1101 1
b10 #
b10 0
1)
1&
#660
0&
#665
b10 5
0)
1&
#670
0&
#675
b1110 1
b100 #
b100 0
1)
1&
#680
0&
#685
b11 5
0)
1&
#690
0&
#695
b1111 1
b1000 #
b1000 0
1)
1&
#700
0&
#705
b100 5
0)
1&
#710
0&
#715
b0 1
b10000 #
b10000 0
1)
1&
#720
0&
#725
b101 5
0)
1&
#730
0&
#735
b1 1
b100000 #
b100000 0
1)
1&
#740
0&
#745
b110 5
0)
1&
#750
0&
#755
b10 1
b1000000 #
b1000000 0
1)
1&
#760
0&
#765
b111 5
0)
1&
#770
0&
#775
1"
b11 1
b10000000 #
b10000000 0
1)
1&
#780
0&
#785
b1000 5
0)
1&
