Daul Port Ram/dp_ram.v
// Code your design here
module tp(clk,rst,en,wr_en,rd_en,wr_addr,rd_addr,wr_data,rd_data);
  
  input clk, rst, wr_en,rd_en,en;
  input [7:0] wr_data;
  input [4:0] wr_addr,rd_addr;
  output reg [7:0] rd_data;
   integer i;
  reg [7:0] mem[15:0];
  always @(posedge clk)
    begin 
      if (!rst)
        begin 
        /*
        fisrt signal to process
         rst low all memory location contain random unknown value */
          for (i=0; i<16;i=1+i)
            begin 
              mem[i] <= 8'hxx;
            end
        end 
      else begin
        if (en==1)
          begin
          /*
          enle pin high after that is for combination 
          rd , wr 
          0,0 memory contain it data 
          1,0 read operation only 
          0,1 writte operation only
          1,1  both operation */
            if (rd_en==1 && wr_en==0)
              begin
                //mem[w_addr] <= wr_data;
                rd_data <= mem[rd_addr];
              end 
            else if (rd_en==0 && wr_en==1)
              begin
                mem[wr_addr] <= wr_data;
               // rd_data <= mem[rd_addr];
              end 
            else if (rd_en==1 && wr_en==1)
              begin 
                // writte and read both operation 
                mem[wr_addr] <= wr_data;
                rd_data <= mem[rd_addr];
              end 
            else 
              begin
                // memory at is value 
                for (i=0; i<16; i=1+i)
                  begin
                    mem[i]<= mem[i];
                  end 
              end 
          end
        // if enable pin is low 
        else begin
       // memory return it original value 
          for (i=0; i<16; i=1+i)
            begin 
              mem[i]<= mem[i];
            end
        end 
      
        end 
      
       end
    
  

  
    
endmodule

Daul Port Ram/tb.v
`timescale 1ns/1ns
`include "dp_ram.v"

module tb;
 reg clk,rst,en,wr_en,rd_en;
// input clk, rst, wr_en,rd_en,en;
  reg [7:0] wr_data;
  reg [4:0] wr_addr,rd_addr;
  wire [7:0] rd_data;
 integer i=0;
 tp dut(clk,rst,en,wr_en,rd_en,wr_addr,rd_addr,wr_data,rd_data);
 
 /*
 task wrt_data(input [data_width-1:0] d_in);
    begin 
        @ (posedge clk)
        cs=1; wr_en =1;
        data_in = d_in;
        $display($time, " data_ enter %0d",data_in);
        @ (posedge clk)
        cs=1; wr_en =0;

    end
  endtask

 */
 // write operation 
  task write( input [7:0]d_in,input [4:0]addr);
  begin
    @(posedge clk)
    en=1;wr_en=1;rd_en=0;
    wr_addr=addr;
    wr_data = d_in;
    $display($time,"data write: address: %h  %h ",wr_data,wr_addr);
    @(posedge clk)
    en=1;wr_en=0;rd_en=0;
  end 
  endtask
// read operation 
  task read(input [4:0] addr_rd);
  begin
    @(posedge clk)
    en=1; rd_en =1; wr_en=0;
    rd_addr=addr_rd;
     $display($time,"data read: address: %h  %h ",rd_data,addr_rd);
     @(posedge clk)
     en=1; rd_en =0; wr_en =0;
  end
  endtask
 initial begin clk=0; end
 always begin clk=#5 ~clk; end

 initial begin
    #10 rst =0;
    #5 rst =1;
    for (i=0; i<20; i=1+i)
    begin 
        
        #10 write($random % 255,i);
    end

    $display(" read operation ");

    for (i=0; i<20; i=1+i)
    begin 
        
        #10 read(i);
    end

    #100 $finish;
 end

initial begin
$dumpvars;
$dumpfile("dp.vcd");
end

endmodule

Daul Port Ram/dump.vcd
$date
	Wed Aug 06 16:45:39 2025
$end
$version
	Icarus Verilog
$end
$timescale
	1ns
$end
$scope module tb $end
$var wire 8 ! rd_data [7:0] $end
$var reg 1 " clk $end
$var reg 1 # en $end
$var reg 5 $ rd_addr [4:0] $end
$var reg 1 % rd_en $end
$var reg 1 & rst $end
$var reg 5 ' wr_addr [4:0] $end
$var reg 8 ( wr_data [7:0] $end
$var reg 1 ) wr_en $end
$var integer 32 * i [31:0] $end
$scope module dut $end
$var wire 1 " clk $end
$var wire 1 # en $end
$var wire 5 + rd_addr [4:0] $end
$var wire 1 % rd_en $end
$var wire 1 & rst $end
$var wire 5 , wr_addr [4:0] $end
$var wire 8 - wr_data [7:0] $end
$var wire 1 ) wr_en $end
$var reg 8 . rd_data [7:0] $end
$var integer 32 / i [31:0] $end
$upscope $end
$scope task read $end
$var reg 5 0 addr_rd [4:0] $end
$upscope $end
$scope task write $end
$var reg 5 1 addr [4:0] $end
$var reg 8 2 d_in [7:0] $end
$upscope $end
$upscope $end
$enddefinitions $end
$comment Show the parameter values. $end
$dumpall
$end
#0
$dumpvars
bx 2
bx 1
bx 0
bx /
bx .
bx -
bx ,
bx +
b0 *
x)
bx (
bx '
x&
x%
bx $
x#
0"
bx !
$end
#5
b10000 /
1"
#10
0"
0&
#15
b10000 /
1"
1&
#20
0"
#25
b10000000 (
b10000000 -
b0 '
b0 ,
0%
1)
1#
1"
b0 1
b10000000 2
#30
0"
#35
b1 *
0)
1"
#40
0"
#45
b101010 (
b101010 -
b1 '
b1 ,
1)
1"
b1 1
b101010 2
#50
0"
#55
b10 *
0)
1"
#60
0"
#65
b11101000 (
b11101000 -
b10 '
b10 ,
1)
1"
b10 1
b11101000 2
#70
0"
#75
b11 *
0)
1"
#80
0"
#85
b1011100 (
b1011100 -
b11 '
b11 ,
1)
1"
b11 1
b1011100 2
#90
0"
#95
b100 *
0)
1"
#100
0"
#105
b1001000 (
b1001000 -
b100 '
b100 ,
1)
1"
b100 1
b1001000 2
#110
0"
#115
b101 *
0)
1"
#120
0"
#125
b1001101 (
b1001101 -
b101 '
b101 ,
1)
1"
b101 1
b1001101 2
#130
0"
#135
b110 *
0)
1"
#140
0"
#145
b1011111 (
b1011111 -
b110 '
b110 ,
1)
1"
b110 1
b1011111 2
#150
0"
#155
b111 *
0)
1"
#160
0"
#165
b100101 (
b100101 -
b111 '
b111 ,
1)
1"
b111 1
b100101 2
#170
0"
#175
b1000 *
0)
1"
#180
0"
#185
b11011000 (
b11011000 -
b1000 '
b1000 ,
1)
1"
b1000 1
b11011000 2
#190
0"
#195
b1001 *
0)
1"
#200
0"
#205
b10111000 (
b10111000 -
b1001 '
b1001 ,
1)
1"
b1001 1
b10111000 2
#210
0"
#215
b1010 *
0)
1"
#220
0"
#225
b11000110 (
b11000110 -
b1010 '
b1010 ,
1)
1"
b1010 1
b11000110 2
#230
0"
#235
b1011 *
0)
1"
#240
0"
#245
b10110110 (
b10110110 -
b1011 '
b1011 ,
1)
1"
b1011 1
b10110110 2
#250
0"
#255
b1100 *
0)
1"
#260
0"
#265
b10010000 (
b10010000 -
b1100 '
b1100 ,
1)
1"
b1100 1
b10010000 2
#270
0"
#275
b1101 *
0)
1"
#280
0"
#285
b11110111 (
b11110111 -
b1101 '
b1101 ,
1)
1"
b1101 1
b11110111 2
#290
0"
#295
b1110 *
0)
1"
#300
0"
#305
b1011110 (
b1011110 -
b1110 '
b1110 ,
1)
1"
b1110 1
b1011110 2
#310
0"
#315
b1111 *
0)
1"
#320
0"
#325
b110 (
b110 -
b1111 '
b1111 ,
1)
1"
b1111 1
b110 2
#330
0"
#335
b10000 *
0)
1"
#340
0"
#345
b100101 (
b100101 -
b10000 '
b10000 ,
1)
1"
b10000 1
b100101 2
#350
0"
#355
b10001 *
0)
1"
#360
0"
#365
b1100110 (
b1100110 -
b10001 '
b10001 ,
1)
1"
b10001 1
b1100110 2
#370
0"
#375
b10010 *
0)
1"
#380
0"
#385
b0 (
b0 -
b10010 '
b10010 ,
1)
1"
b10010 1
b0 2
#390
0"
#395
b10011 *
0)
1"
#400
0"
#405
b1111000 (
b1111000 -
b10011 '
b10011 ,
1)
1"
b10011 1
b1111000 2
#410
0"
#415
b0 *
0)
1"
#420
0"
#425
b10000000 !
b10000000 .
b0 $
b0 +
1%
1"
b0 0
#430
0"
#435
b1 *
0%
1"
#440
0"
#445
b101010 !
b101010 .
b1 $
b1 +
1%
1"
b1 0
#450
0"
#455
b10 *
0%
1"
#460
0"
#465
b11101000 !
b11101000 .
b10 $
b10 +
1%
1"
b10 0
#470
0"
#475
b11 *
0%
1"
#480
0"
#485
b1011100 !
b1011100 .
b11 $
b11 +
1%
1"
b11 0
#490
0"
#495
b100 *
0%
1"
#500
0"
#505
b1001000 !
b1001000 .
b100 $
b100 +
1%
1"
b100 0
#510
0"
#515
b101 *
0%
1"
#520
0"
#525
b1001101 !
b1001101 .
b101 $
b101 +
1%
1"
b101 0
#530
0"
#535
b110 *
0%
1"
#540
0"
#545
b1011111 !
b1011111 .
b110 $
b110 +
1%
1"
b110 0
#550
0"
#555
b111 *
0%
1"
#560
0"
#565
b100101 !
b100101 .
b111 $
b111 +
1%
1"
b111 0
#570
0"
#575
b1000 *
0%
1"
#580
0"
#585
b11011000 !
b11011000 .
b1000 $
b1000 +
1%
1"
b1000 0
#590
0"
#595
b1001 *
0%
1"
#600
0"
#605
b10111000 !
b10111000 .
b1001 $
b1001 +
1%
1"
b1001 0
#610
0"
#615
b1010 *
0%
1"
#620
0"
#625
b11000110 !
b11000110 .
b1010 $
b1010 +
1%
1"
b1010 0
#630
0"
#635
b1011 *
0%
1"
#640
0"
#645
b10110110 !
b10110110 .
b1011 $
b1011 +
1%
1"
b1011 0
#650
0"
#655
b1100 *
0%
1"
#660
0"
#665
b10010000 !
b10010000 .
b1100 $
b1100 +
1%
1"
b1100 0
#670
0"
#675
b1101 *
0%
1"
#680
0"
#685
b11110111 !
b11110111 .
b1101 $
b1101 +
1%
1"
b1101 0
#690
0"
#695
b1110 *
0%
1"
#700
0"
#705
b1011110 !
b1011110 .
b1110 $
b1110 +
1%
1"
b1110 0
#710
0"
#715
b1111 *
0%
1"
#720
0"
#725
b110 !
b110 .
b1111 $
b1111 +
1%
1"
b1111 0
#730
0"
#735
b10000 *
0%
1"
#740
0"
#745
bx !
bx .
b10000 $
b10000 +
1%
1"
b10000 0
#750
0"
#755
b10001 *
0%
1"
#760
0"
#765
b10001 $
b10001 +
1%
1"
b10001 0
#770
0"
#775
b10010 *
0%
1"
#780
0"
#785
b10010 $
b10010 +
1%
1"
b10010 0
#790
0"
#795
b10011 *
0%
1"
#800
0"
#805
b10011 $
b10011 +
1%
1"
b10011 0
#810
0"
#815
b10100 *
0%
1"
#820
0"
#825
b10000 /
1"
#830
0"
#835
b10000 /
1"
#840
0"
#845
b10000 /
1"
#850
0"
#855
b10000 /
1"
#860
0"
#865
b10000 /
1"
#870
0"
#875
b10000 /
1"
#880
0"
#885
b10000 /
1"
#890
0"
#895
b10000 /
1"
#900
0"
#905
b10000 /
1"
#910
0"
#915
b10000 /
1"
