clock/clock.v
// started a cock in geenration in verilog with using directive 
`timescale 1ns/1ps
module clock_gen(
    input enable ,
    output reg clk
);
parameter FREQ =1000000 ; // in Khz
parameter PHASE = 0; // in degree 
parameter DUTY = 50;// in percentage 
localparam real clk_pd = 1.0/(FREQ*1e3)*1e9; // convert time period in neno second
 localparam real clk_on = DUTY/100.0*clk_pd; // one period time in ns
localparam real clk_off = (100.0-DUTY)/100.0*clk_pd;// off period time in ns
 localparam real quarter = clk_pd/4; // 1/4 part of period 
 localparam real start_dly = quarter*PHASE/90.0;// delay for phase 

reg start_clk;

initial begin
    $display(" frequency = %0d khz",FREQ);
    $display(" phase  = %0d deg ",PHASE);
    $display("duty = %0d %%",DUTY);
    $display(" period = %0.3f ns",clk_pd);
    $display(" clk on = %0.3f ns", clk_on);
    $display(" clk off = %0.3f ns", clk_off);
    $display(" quarte  = %0.3f ns", quarter);
    $display("start dly = %0.3f ns", start_dly);
end

initial begin
    clk <=  0;
    start_clk <= 0;
end

always @(posedge enable or negedge enable) begin
    if (enable) begin
    #(start_dly) start_clk =1; end
    else 
    begin
        #(start_dly) start_clk =0;
    end
    
end
 
 always @(posedge start_clk) begin
    if (start_clk)
    begin
        clk=1;
        while (start_clk)
         begin
            #(clk_on) clk =0;
            #(clk_off) clk =1;
         end
         clk =0;
    end
 end
endmodule

clock/clocktb.v
`include "clock.v"
`timescale 1ns/1ps
module tb;
    wire clk1;
    wire clk2;
    wire clk3;
    wire clk4;
  reg enable ;
reg [2:0]  dly;
// for clock eneration 
reg [31:0] seed;
clock_gen u0(enable, clk1);
clock_gen #(.FREQ(200000)) u1(enable,clk2);
clock_gen #(.FREQ(400000)) u2(enable,clk3);
clock_gen #(.FREQ(600000)) u3(enable,clk4);
// vcd file create in this test bench 
initial begin
    $dumpfile("clock.vcd");
    $dumpvars(0,tb);
end
 initial begin
    enable <=0;
    for (integer i=0; i<10; i=1+i)
    begin
        dly = $random;
        #(dly) enable <= ~enable;
         $display("i=%0d dly =%0d",i,dly);
         #50;
         
        
    end
     #50 $finish();
  end

 endmodule

clock/clock.vcd
$date
	Sun Apr 13 15:42:36 2025
$end
$version
	Icarus Verilog
$end
$timescale
	1ps
$end
$scope module tb $end
$var wire 1 ! clk4 $end
$var wire 1 " clk3 $end
$var wire 1 # clk2 $end
$var wire 1 $ clk1 $end
$var reg 3 % dly [2:0] $end
$var reg 1 & enable $end
$scope module u0 $end
$var wire 1 & enable $end
$var parameter 32 ' DUTY $end
$var parameter 32 ( FREQ $end
$var parameter 32 ) PHASE $end
$var real 1 * clk_off $end
$var real 1 + clk_on $end
$var real 1 , clk_pd $end
$var real 1 - quarter $end
$var real 1 . start_dly $end
$var reg 1 $ clk $end
$var reg 1 / start_clk $end
$upscope $end
$scope module u1 $end
$var wire 1 & enable $end
$var parameter 32 0 DUTY $end
$var parameter 32 1 FREQ $end
$var parameter 32 2 PHASE $end
$var real 1 3 clk_off $end
$var real 1 4 clk_on $end
$var real 1 5 clk_pd $end
$var real 1 6 quarter $end
$var real 1 7 start_dly $end
$var reg 1 # clk $end
$var reg 1 8 start_clk $end
$upscope $end
$scope module u2 $end
$var wire 1 & enable $end
$var parameter 32 9 DUTY $end
$var parameter 32 : FREQ $end
$var parameter 32 ; PHASE $end
$var real 1 < clk_off $end
$var real 1 = clk_on $end
$var real 1 > clk_pd $end
$var real 1 ? quarter $end
$var real 1 @ start_dly $end
$var reg 1 " clk $end
$var reg 1 A start_clk $end
$upscope $end
$scope module u3 $end
$var wire 1 & enable $end
$var parameter 32 B DUTY $end
$var parameter 32 C FREQ $end
$var parameter 32 D PHASE $end
$var real 1 E clk_off $end
$var real 1 F clk_on $end
$var real 1 G clk_pd $end
$var real 1 H quarter $end
$var real 1 I start_dly $end
$var reg 1 ! clk $end
$var reg 1 J start_clk $end
$upscope $end
$scope begin $ivl_for_loop0 $end
$var integer 32 K i [31:0] $end
$upscope $end
$upscope $end
$enddefinitions $end
$comment Show the parameter values. $end
$dumpall
r0 I
r0.4166666666666667 H
r1.666666666666667 G
r0.8333333333333334 F
r0.8333333333333334 E
b0 D
b10010010011111000000 C
b110010 B
r0 @
r0.625 ?
r2.5 >
r1.25 =
r1.25 <
b0 ;
b1100001101010000000 :
b110010 9
r0 7
r1.25 6
r5 5
r2.5 4
r2.5 3
b0 2
b110000110101000000 1
b110010 0
r0 .
r0.25 -
r1 ,
r0.5 +
r0.5 *
b0 )
b11110100001001000000 (
b110010 '
$end
#0
$dumpvars
b0 K
0J
0A
08
0/
0&
b100 %
0$
0#
0"
0!
$end
#4000
1!
1"
1#
1$
1J
1A
18
1/
1&
#4500
0$
#4833
0!
#5000
1$
#5250
0"
#5500
0$
#5666
1!
#6000
1$
#6499
0!
#6500
0$
1"
0#
#7000
1$
#7332
1!
#7500
0$
#7750
0"
#8000
1$
#8165
0!
#8500
0$
#8998
1!
#9000
1$
1"
1#
#9500
0$
#9831
0!
#10000
1$
#10250
0"
#10500
0$
#10664
1!
#11000
1$
#11497
0!
#11500
0$
1"
0#
#12000
1$
#12330
1!
#12500
0$
#12750
0"
#13000
1$
#13163
0!
#13500
0$
#13996
1!
#14000
1$
1"
1#
#14500
0$
#14829
0!
#15000
1$
#15250
0"
#15500
0$
#15662
1!
#16000
1$
#16495
0!
#16500
0$
1"
0#
#17000
1$
#17328
1!
#17500
0$
#17750
0"
#18000
1$
#18161
0!
#18500
0$
#18994
1!
#19000
1$
1"
1#
#19500
0$
#19827
0!
#20000
1$
#20250
0"
#20500
0$
#20660
1!
#21000
1$
#21493
0!
#21500
0$
1"
0#
#22000
1$
#22326
1!
#22500
0$
#22750
0"
#23000
1$
#23159
0!
#23500
0$
#23992
1!
#24000
1$
1"
1#
#24500
0$
#24825
0!
#25000
1$
#25250
0"
#25500
0$
#25658
1!
#26000
1$
#26491
0!
#26500
0$
1"
0#
#27000
1$
#27324
1!
#27500
0$
#27750
0"
#28000
1$
#28157
0!
#28500
0$
#28990
1!
#29000
1$
1"
1#
#29500
0$
#29823
0!
#30000
1$
#30250
0"
#30500
0$
#30656
1!
#31000
1$
#31489
0!
#31500
0$
1"
0#
#32000
1$
#32322
1!
#32500
0$
#32750
0"
#33000
1$
#33155
0!
#33500
0$
#33988
1!
#34000
1$
1"
1#
#34500
0$
#34821
0!
#35000
1$
#35250
0"
#35500
0$
#35654
1!
#36000
1$
#36487
0!
#36500
0$
1"
0#
#37000
1$
#37320
1!
#37500
0$
#37750
0"
#38000
1$
#38153
0!
#38500
0$
#38986
1!
#39000
1$
1"
1#
#39500
0$
#39819
0!
#40000
1$
#40250
0"
#40500
0$
#40652
1!
#41000
1$
#41485
0!
#41500
0$
1"
0#
#42000
1$
#42318
1!
#42500
0$
#42750
0"
#43000
1$
#43151
0!
#43500
0$
#43984
1!
#44000
1$
1"
1#
#44500
0$
#44817
0!
#45000
1$
#45250
0"
#45500
0$
#45650
1!
#46000
1$
#46483
0!
#46500
0$
1"
0#
#47000
1$
#47316
1!
#47500
0$
#47750
0"
#48000
1$
#48149
0!
#48500
0$
#48982
1!
#49000
1$
1"
1#
#49500
0$
#49815
0!
#50000
1$
#50250
0"
#50500
0$
#50648
1!
#51000
1$
#51481
0!
#51500
0$
1"
0#
#52000
1$
#52314
1!
#52500
0$
#52750
0"
#53000
1$
#53147
0!
#53500
0$
#53980
1!
#54000
1$
1"
1#
b1 %
b1 K
#54500
0$
#54813
0!
#55000
0/
08
0A
0J
0&
1$
#55250
0"
#55500
0$
#55646
0!
#56000
0$
#56500
0"
0#
#59000
0#
#105000
b10 K
#106000
1!
1"
1#
1$
1J
1A
18
1/
1&
#106500
0$
#106833
0!
#107000
1$
#107250
0"
#107500
0$
#107666
1!
#108000
1$
#108499
0!
#108500
0$
1"
0#
#109000
1$
#109332
1!
#109500
0$
#109750
0"
#110000
1$
#110165
0!
#110500
0$
#110998
1!
#111000
1$
1"
1#
#111500
0$
#111831
0!
#112000
1$
#112250
0"
#112500
0$
#112664
1!
#113000
1$
#113497
0!
#113500
0$
1"
0#
#114000
1$
#114330
1!
#114500
0$
#114750
0"
#115000
1$
#115163
0!
#115500
0$
#115996
1!
#116000
1$
1"
1#
#116500
0$
#116829
0!
#117000
1$
#117250
0"
#117500
0$
#117662
1!
#118000
1$
#118495
0!
#118500
0$
1"
0#
#119000
1$
#119328
1!
#119500
0$
#119750
0"
#120000
1$
#120161
0!
#120500
0$
#120994
1!
#121000
1$
1"
1#
#121500
0$
#121827
0!
#122000
1$
#122250
0"
#122500
0$
#122660
1!
#123000
1$
#123493
0!
#123500
0$
1"
0#
#124000
1$
#124326
1!
#124500
0$
#124750
0"
#125000
1$
#125159
0!
#125500
0$
#125992
1!
#126000
1$
1"
1#
#126500
0$
#126825
0!
#127000
1$
#127250
0"
#127500
0$
#127658
1!
#128000
1$
#128491
0!
#128500
0$
1"
0#
#129000
1$
#129324
1!
#129500
0$
#129750
0"
#130000
1$
#130157
0!
#130500
0$
#130990
1!
#131000
1$
1"
1#
#131500
0$
#131823
0!
#132000
1$
#132250
0"
#132500
0$
#132656
1!
#133000
1$
#133489
0!
#133500
0$
1"
0#
#134000
1$
#134322
1!
#134500
0$
#134750
0"
#135000
1$
#135155
0!
#135500
0$
#135988
1!
#136000
1$
1"
1#
#136500
0$
#136821
0!
#137000
1$
#137250
0"
#137500
0$
#137654
1!
#138000
1$
#138487
0!
#138500
0$
1"
0#
#139000
1$
#139320
1!
#139500
0$
#139750
0"
#140000
1$
#140153
0!
#140500
0$
#140986
1!
#141000
1$
1"
1#
#141500
0$
#141819
0!
#142000
1$
#142250
0"
#142500
0$
#142652
1!
#143000
1$
#143485
0!
#143500
0$
1"
0#
#144000
1$
#144318
1!
#144500
0$
#144750
0"
#145000
1$
#145151
0!
#145500
0$
#145984
1!
#146000
1$
1"
1#
#146500
0$
#146817
0!
#147000
1$
#147250
0"
#147500
0$
#147650
1!
#148000
1$
#148483
0!
#148500
0$
1"
0#
#149000
1$
#149316
1!
#149500
0$
#149750
0"
#150000
1$
#150149
0!
#150500
0$
#150982
1!
#151000
1$
1"
1#
#151500
0$
#151815
0!
#152000
1$
#152250
0"
#152500
0$
#152648
1!
#153000
1$
#153481
0!
#153500
0$
1"
0#
#154000
1$
#154314
1!
#154500
0$
#154750
0"
#155000
1$
#155147
0!
#155500
0$
#155980
1!
#156000
1$
1"
1#
b11 %
b11 K
#156500
0$
#156813
0!
#157000
1$
#157250
0"
#157500
0$
#157646
1!
#158000
1$
#158479
0!
#158500
0$
1"
0#
#159000
0/
08
0A
0J
0&
1$
#159312
0!
#159500
0$
#159750
0"
#160000
0$
#161000
0"
0#
#209000
b101 %
b100 K
#214000
1!
1"
1#
1$
1J
1A
18
1/
1&
