clock/clock.v
// started a cock in geenration in verilog with using directive 
`timescale 1ns/1ps
module clock_gen(
    input enable ,
    output reg clk
);
parameter FREQ =1000000 ; // in Khz
parameter PHASE = 0; // in degree 
parameter DUTY = 50;// in percentage 
localparam real clk_pd = 1.0/(FREQ*1e3)*1e9; // convert time period in neno second
 localparam real clk_on = DUTY/100.0*clk_pd; // one period time in ns
localparam real clk_off = (100.0-DUTY)/100.0*clk_pd;// off period time in ns
 localparam real quarter = clk_pd/4; // 1/4 part of period 
 localparam real start_dly = quarter*PHASE/90.0;// delay for phase 

reg start_clk;

initial begin
    $display(" frequency = %0d khz",FREQ);
    $display(" phase  = %0d deg ",PHASE);
    $display("duty = %0d %%",DUTY);
    $display(" period = %0.3f ns",clk_pd);
    $display(" clk on = %0.3f ns", clk_on);
    $display(" clk off = %0.3f ns", clk_off);
    $display(" quarte  = %0.3f ns", quarter);
    $display("start dly = %0.3f ns", start_dly);
end

initial begin
    clk <=  0;
    start_clk <= 0;
end

always @(posedge enable or negedge enable) begin
    if (enable) begin
    #(start_dly) start_clk =1; end
    else 
    begin
        #(start_dly) start_clk =0;
    end
    
end
 
 always @(posedge start_clk) begin
    if (start_clk)
    begin
        clk=1;
        while (start_clk)
         begin
            #(clk_on) clk =0;
            #(clk_off) clk =1;
         end
         clk =0;
    end
 end
endmodule

clock/duty.v
`include "clock.v"
module tb;
wire clk1;
wire clk2;
wire clk3;
wire clk4;
reg enable ;
reg [7:0] dly;
clock_gen u0(enable,clk1);
clock_gen #(.FREQ(50000), .DUTY(25)) u1 (enable, clk2);

clock_gen #(.FREQ(50000), .DUTY(75)) u2 (enable, clk3);
clock_gen #(.FREQ(50000), .DUTY(60)) u3 (enable, clk4);

initial begin
    $dumpfile("duty.vcd");
    $dumpvars(0,tb);
end
initial begin
    enable <= 0;
    repeat(10)
    begin
        dly =$random;
        #(dly) enable <= ~enable;
        $display("clock =%0t dly =%0d",$time,dly);

    end
    #50 $finish();
end

endmodule

clock/phase.vcd
$date
	Sun Apr 13 16:15:41 2025
$end
$version
	Icarus Verilog
$end
$timescale
	1ps
$end
$scope module tb $end
$var wire 1 ! clk4 $end
$var wire 1 " clk3 $end
$var wire 1 # clk2 $end
$var wire 1 $ clk1 $end
$var reg 8 % dly [7:0] $end
$var reg 1 & enable $end
$scope module u0 $end
$var wire 1 & enable $end
$var parameter 32 ' DUTY $end
$var parameter 32 ( FREQ $end
$var parameter 32 ) PHASE $end
$var real 1 * clk_off $end
$var real 1 + clk_on $end
$var real 1 , clk_pd $end
$var real 1 - quarter $end
$var real 1 . start_dly $end
$var reg 1 $ clk $end
$var reg 1 / start_clk $end
$upscope $end
$scope module u1 $end
$var wire 1 & enable $end
$var parameter 32 0 DUTY $end
$var parameter 32 1 FREQ $end
$var parameter 32 2 PHASE $end
$var real 1 3 clk_off $end
$var real 1 4 clk_on $end
$var real 1 5 clk_pd $end
$var real 1 6 quarter $end
$var real 1 7 start_dly $end
$var reg 1 # clk $end
$var reg 1 8 start_clk $end
$upscope $end
$scope module u2 $end
$var wire 1 & enable $end
$var parameter 32 9 DUTY $end
$var parameter 32 : FREQ $end
$var parameter 32 ; PHASE $end
$var real 1 < clk_off $end
$var real 1 = clk_on $end
$var real 1 > clk_pd $end
$var real 1 ? quarter $end
$var real 1 @ start_dly $end
$var reg 1 " clk $end
$var reg 1 A start_clk $end
$upscope $end
$scope module u3 $end
$var wire 1 & enable $end
$var parameter 32 B DUTY $end
$var parameter 32 C FREQ $end
$var parameter 32 D PHASE $end
$var real 1 E clk_off $end
$var real 1 F clk_on $end
$var real 1 G clk_pd $end
$var real 1 H quarter $end
$var real 1 I start_dly $end
$var reg 1 ! clk $end
$var reg 1 J start_clk $end
$upscope $end
$upscope $end
$enddefinitions $end
$comment Show the parameter values. $end
$dumpall
r2.5 I
r5 H
r20 G
r10 F
r10 E
b101101 D
b1100001101010000 C
b110010 B
r10 @
r5 ?
r20 >
r10 =
r10 <
b10110100 ;
b1100001101010000 :
b110010 9
r5 7
r5 6
r20 5
r10 4
r10 3
b1011010 2
b1100001101010000 1
b110010 0
r0 .
r0.25 -
r1 ,
r0.5 +
r0.5 *
b0 )
b11110100001001000000 (
b110010 '
$end
#0
$dumpvars
0J
0A
08
0/
0&
b100100 %
0$
0#
0"
0!
$end
#36000
1$
1/
1&
b10000001 %
#36500
0$
#37000
1$
#37500
0$
#38000
1$
#38500
1!
0$
1J
#39000
1$
#39500
0$
#40000
1$
#40500
0$
#41000
1#
1$
18
#41500
0$
#42000
1$
#42500
0$
#43000
1$
#43500
0$
#44000
1$
#44500
0$
#45000
1$
#45500
0$
#46000
1"
1$
1A
#46500
0$
#47000
1$
#47500
0$
#48000
1$
#48500
0$
0!
#49000
1$
#49500
0$
#50000
1$
#50500
0$
#51000
1$
0#
#51500
0$
#52000
1$
#52500
0$
#53000
1$
#53500
0$
#54000
1$
#54500
0$
#55000
1$
#55500
0$
#56000
1$
0"
#56500
0$
#57000
1$
#57500
0$
#58000
1$
#58500
0$
1!
#59000
1$
#59500
0$
#60000
1$
#60500
0$
#61000
1$
1#
#61500
0$
#62000
1$
#62500
0$
#63000
1$
#63500
0$
#64000
1$
#64500
0$
#65000
1$
#65500
0$
#66000
1$
1"
#66500
0$
#67000
1$
#67500
0$
#68000
1$
#68500
0$
0!
#69000
1$
#69500
0$
#70000
1$
#70500
0$
#71000
1$
0#
#71500
0$
#72000
1$
#72500
0$
#73000
1$
#73500
0$
#74000
1$
#74500
0$
#75000
1$
#75500
0$
#76000
1$
0"
#76500
0$
#77000
1$
#77500
0$
#78000
1$
#78500
0$
1!
#79000
1$
#79500
0$
#80000
1$
#80500
0$
#81000
1$
1#
#81500
0$
#82000
1$
#82500
0$
#83000
1$
#83500
0$
#84000
1$
#84500
0$
#85000
1$
#85500
0$
#86000
1$
1"
#86500
0$
#87000
1$
#87500
0$
#88000
1$
#88500
0$
0!
#89000
1$
#89500
0$
#90000
1$
#90500
0$
#91000
1$
0#
#91500
0$
#92000
1$
#92500
0$
#93000
1$
#93500
0$
#94000
1$
#94500
0$
#95000
1$
#95500
0$
#96000
1$
0"
#96500
0$
#97000
1$
#97500
0$
#98000
1$
#98500
0$
1!
#99000
1$
#99500
0$
#100000
1$
#100500
0$
#101000
1$
1#
#101500
0$
#102000
1$
#102500
0$
#103000
1$
#103500
0$
#104000
1$
#104500
0$
#105000
1$
#105500
0$
#106000
1$
1"
#106500
0$
#107000
1$
#107500
0$
#108000
1$
#108500
0$
0!
#109000
1$
#109500
0$
#110000
1$
#110500
0$
#111000
1$
0#
#111500
0$
#112000
1$
#112500
0$
#113000
1$
#113500
0$
#114000
1$
#114500
0$
#115000
1$
#115500
0$
#116000
1$
0"
#116500
0$
#117000
1$
#117500
0$
#118000
1$
#118500
0$
1!
#119000
1$
#119500
0$
#120000
1$
#120500
0$
#121000
1$
1#
#121500
0$
#122000
1$
#122500
0$
#123000
1$
#123500
0$
#124000
1$
#124500
0$
#125000
1$
#125500
0$
#126000
1$
1"
#126500
0$
#127000
1$
#127500
0$
#128000
1$
#128500
0$
0!
#129000
1$
#129500
0$
#130000
1$
#130500
0$
#131000
1$
0#
#131500
0$
#132000
1$
#132500
0$
#133000
1$
#133500
0$
#134000
1$
#134500
0$
#135000
1$
#135500
0$
#136000
1$
0"
#136500
0$
#137000
1$
#137500
0$
#138000
1$
#138500
0$
1!
#139000
1$
#139500
0$
#140000
1$
#140500
0$
#141000
1$
1#
#141500
0$
#142000
1$
#142500
0$
#143000
1$
#143500
0$
#144000
1$
#144500
0$
#145000
1$
#145500
0$
#146000
1$
1"
#146500
0$
#147000
1$
#147500
0$
#148000
1$
#148500
0$
0!
#149000
1$
#149500
0$
#150000
1$
#150500
0$
#151000
1$
0#
#151500
0$
#152000
1$
#152500
0$
#153000
1$
#153500
0$
#154000
1$
#154500
0$
#155000
1$
#155500
0$
#156000
1$
0"
#156500
0$
#157000
1$
#157500
0$
#158000
1$
#158500
0$
1!
#159000
1$
#159500
0$
#160000
1$
#160500
0$
#161000
1$
1#
#161500
0$
#162000
1$
#162500
0$
#163000
1$
#163500
0$
#164000
1$
#164500
0$
#165000
0/
0&
1$
b1001 %
#165500
0$
#166000
0$
1"
#167500
0J
#168500
0!
#170000
08
#171000
0#
#174000
1$
1/
1&
b1100011 %
#174500
0$
#175000
1$
0A
#175500
0$
#176000
1$
0"
#176500
0$
1J
#177000
1$
#177500
0$
#178000
1$
#178500
0$
1!
#179000
1$
18
#179500
0$
#180000
1$
#180500
0$
#181000
1$
1#
#181500
0$
#182000
1$
#182500
0$
#183000
1$
#183500
0$
#184000
1$
#184500
0$
#185000
1$
#185500
0$
#186000
1$
0"
#186500
0$
#187000
1$
#187500
0$
#188000
1$
#188500
0$
0!
#189000
1$
#189500
0$
#190000
1$
#190500
0$
#191000
1$
0#
#191500
0$
#192000
1$
#192500
0$
#193000
1$
#193500
0$
#194000
1$
#194500
0$
#195000
1$
#195500
0$
#196000
1$
#196500
0$
#197000
1$
#197500
0$
#198000
1$
#198500
0$
1!
#199000
1$
#199500
0$
#200000
1$
#200500
0$
#201000
1$
1#
#201500
0$
#202000
1$
#202500
0$
#203000
1$
#203500
0$
#204000
1$
#204500
0$
#205000
1$
#205500
0$
#206000
1$
#206500
0$
#207000
1$
#207500
0$
#208000
1$
#208500
0$
0!
#209000
1$
#209500
0$
#210000
1$
#210500
0$
#211000
1$
0#
#211500
0$
#212000
1$
#212500
0$
#213000
1$
#213500
0$
#214000
1$
#214500
0$
#215000
1$
#215500
0$
#216000
1$
#216500
0$
#217000
1$
#217500
0$
#218000
1$
#218500
0$
1!
#219000
1$
#219500
0$
#220000
1$
#220500
0$
#221000
1$
1#
#221500
0$
#222000
1$
#222500
0$
#223000
1$
#223500
0$
#224000
1$
#224500
0$
#225000
1$
#225500
0$
#226000
1$
#226500
0$
#227000
1$
#227500
0$
#228000
1$
#228500
0$
0!
#229000
1$
#229500
0$
#230000
1$
#230500
0$
#231000
1$
0#
#231500
0$
#232000
1$
#232500
0$
#233000
1$
#233500
0$
#234000
1$
#234500
0$
#235000
1$
#235500
0$
#236000
1$
#236500
0$
#237000
1$
#237500
0$
#238000
1$
#238500
0$
1!
#239000
1$
#239500
0$
#240000
1$
#240500
0$
#241000
1$
1#
#241500
0$
#242000
1$
#242500
0$
#243000
1$
#243500
0$
#244000
1$
#244500
0$
#245000
1$
#245500
0$
#246000
1$
#246500
0$
#247000
1$
#247500
0$
#248000
1$
#248500
0$
0!
#249000
1$
#249500
0$
#250000
1$
#250500
0$
#251000
1$
0#
#251500
0$
#252000
1$
#252500
0$
#253000
1$
#253500
0$
#254000
1$
#254500
0$
#255000
1$
#255500
0$
#256000
1$
#256500
0$
#257000
1$
#257500
0$
#258000
1$
#258500
0$
1!
#259000
1$
#259500
0$
#260000
1$
#260500
0$
#261000
1$
1#
#261500
0$
#262000
1$
#262500
0$
#263000
1$
#263500
0$
#264000
1$
#264500
0$
#265000
1$
#265500
0$
#266000
1$
#266500
0$
#267000
1$
#267500
0$
#268000
1$
#268500
0$
0!
#269000
1$
#269500
0$
#270000
1$
#270500
0$
#271000
1$
0#
#271500
0$
#272000
1$
#272500
0$
#273000
0/
0&
1$
b1101 %
#273500
0$
#274000
0$
#275500
0J
#278000
08
#278500
0!
#281000
0#
#286000
1$
1/
1&
b10001101 %
#286500
0$
#287000
1$
#287500
0$
#288000
1$
#288500
1!
0$
1J
#289000
1$
#289500
0$
#290000
1$
#290500
0$
#291000
1#
1$
18
#291500
0$
#292000
1$
#292500
0$
#293000
1$
#293500
0$
#294000
1$
#294500
0$
#295000
1$
#295500
0$
#296000
1"
1$
1A
#296500
0$
#297000
1$
#297500
0$
#298000
1$
#298500
0$
0!
#299000
1$
#299500
0$
#300000
1$
#300500
0$
#301000
1$
0#
#301500
0$
#302000
1$
#302500
0$
#303000
1$
#303500
0$
#304000
1$
#304500
0$
#305000
1$
#305500
0$
#306000
1$
0"
#306500
0$
#307000
1$
#307500
0$
#308000
1$
#308500
0$
1!
#309000
1$
#309500
0$
#310000
1$
#310500
0$
#311000
1$
1#
#311500
0$
#312000
1$
#312500
0$
#313000
1$
#313500
0$
#314000
1$
#314500
0$
#315000
1$
#315500
0$
#316000
1$
1"
#316500
0$
#317000
1$
#317500
0$
#318000
1$
#318500
0$
0!
#319000
1$
#319500
0$
#320000
1$
#320500
0$
#321000
1$
0#
#321500
0$
#322000
1$
#322500
0$
#323000
1$
#323500
0$
#324000
1$
#324500
0$
#325000
1$
#325500
0$
#326000
1$
0"
#326500
0$
#327000
1$
#327500
0$
#328000
1$
#328500
0$
1!
#329000
1$
#329500
0$
#330000
1$
#330500
0$
#331000
1$
1#
#331500
0$
#332000
1$
#332500
0$
#333000
1$
#333500
0$
#334000
1$
#334500
0$
#335000
1$
#335500
0$
#336000
1$
1"
#336500
0$
#337000
1$
#337500
0$
#338000
1$
#338500
0$
0!
#339000
1$
#339500
0$
#340000
1$
#340500
0$
#341000
1$
0#
#341500
0$
#342000
1$
#342500
0$
#343000
1$
#343500
0$
#344000
1$
#344500
0$
#345000
1$
#345500
0$
#346000
1$
0"
#346500
0$
#347000
1$
#347500
0$
#348000
1$
#348500
0$
1!
#349000
1$
#349500
0$
#350000
1$
#350500
0$
#351000
1$
1#
#351500
0$
#352000
1$
#352500
0$
#353000
1$
#353500
0$
#354000
1$
#354500
0$
#355000
1$
#355500
0$
#356000
1$
1"
#356500
0$
#357000
1$
#357500
0$
#358000
1$
#358500
0$
0!
#359000
1$
#359500
0$
#360000
1$
#360500
0$
#361000
1$
0#
#361500
0$
#362000
1$
#362500
0$
#363000
1$
#363500
0$
#364000
1$
#364500
0$
#365000
1$
#365500
0$
#366000
1$
0"
#366500
0$
#367000
1$
#367500
0$
#368000
1$
#368500
0$
1!
#369000
1$
#369500
0$
#370000
1$
#370500
0$
#371000
1$
1#
#371500
0$
#372000
1$
#372500
0$
#373000
1$
#373500
0$
#374000
1$
#374500
0$
#375000
1$
#375500
0$
#376000
1$
1"
#376500
0$
#377000
1$
#377500
0$
#378000
1$
#378500
0$
0!
#379000
1$
#379500
0$
#380000
1$
#380500
0$
#381000
1$
0#
#381500
0$
#382000
1$
#382500
0$
#383000
1$
#383500
0$
#384000
1$
#384500
0$
#385000
1$
#385500
0$
#386000
1$
0"
#386500
0$
#387000
1$
#387500
0$
#388000
1$
#388500
0$
1!
#389000
1$
#389500
0$
#390000
1$
#390500
0$
#391000
1$
1#
#391500
0$
#392000
1$
#392500
0$
#393000
1$
#393500
0$
#394000
1$
#394500
0$
#395000
1$
#395500
0$
#396000
1$
1"
#396500
0$
#397000
1$
#397500
0$
#398000
1$
#398500
0$
0!
#399000
1$
#399500
0$
#400000
1$
#400500
0$
#401000
1$
0#
#401500
0$
#402000
1$
#402500
0$
#403000
1$
#403500
0$
#404000
1$
#404500
0$
#405000
1$
#405500
0$
#406000
1$
0"
#406500
0$
#407000
1$
#407500
0$
#408000
1$
#408500
0$
1!
#409000
1$
#409500
0$
#410000
1$
#410500
0$
#411000
1$
1#
#411500
0$
#412000
1$
#412500
0$
#413000
1$
#413500
0$
#414000
1$
#414500
0$
#415000
1$
#415500
0$
#416000
1$
1"
#416500
0$
#417000
1$
#417500
0$
#418000
1$
#418500
0$
0!
#419000
1$
#419500
0$
#420000
1$
#420500
0$
#421000
1$
0#
#421500
0$
#422000
1$
#422500
0$
#423000
1$
#423500
0$
#424000
1$
#424500
0$
#425000
1$
#425500
0$
#426000
1$
0"
#426500
0$
#427000
0/
0&
1$
b1100101 %
#427500
0$
#428000
0$
#428500
1!
#429500
0J
#431000
1#
#432000
08
#436000
1"
#437000
0A
#438500
0!
#441000
0#
#446000
0"
#448500
0!
#451000
0#
#456000
0"
#528000
1$
1/
1&
b10010 %
#528500
0$
#529000
1$
#529500
0$
#530000
1$
#530500
1!
0$
1J
#531000
1$
#531500
0$
#532000
1$
#532500
0$
#533000
1#
1$
18
#533500
0$
#534000
1$
#534500
0$
#535000
1$
#535500
0$
#536000
1$
#536500
0$
#537000
1$
#537500
0$
#538000
1"
1$
1A
#538500
0$
#539000
1$
#539500
0$
#540000
1$
#540500
0$
0!
#541000
1$
#541500
0$
#542000
1$
#542500
0$
#543000
1$
0#
#543500
0$
#544000
1$
#544500
0$
#545000
1$
#545500
0$
#546000
0/
0&
1$
b1 %
#546500
0$
#547000
1/
1&
1$
b1101 %
#547500
0$
#548000
1$
0"
#548500
0$
0J
#549000
1$
#549500
0$
#550000
1$
#550500
0$
0!
#551000
1$
08
#551500
0$
#552000
1$
#552500
0$
#553000
1$
0#
#553500
0$
#554000
1$
#554500
0$
#555000
1$
#555500
0$
#556000
1$
0A
#556500
0$
#557000
1$
#557500
0$
#558000
1$
0"
#558500
0$
#559000
1$
#559500
0$
#560000
0/
0&
1$
